simple_build_dgcode-1.7.2.dist-info/licenses/LICENSE
simplebuild_dgcode/__init__.py
simplebuild_dgcode/_cli.py
simplebuild_dgcode/_determine_version.py
simplebuild_dgcode/_utils.py
simplebuild_dgcode/newsimproject.py
simplebuild_dgcode/simplebuild_bundle_list.py
simplebuild_dgcode/data/pkgs/simplebuild.cfg
simplebuild_dgcode/data/pkgs/DGCodeRecommended/pkg.info
simplebuild_dgcode/data/pkgs/DGCodeRecommendedNoGUI/pkg.info
simplebuild_dgcode/data/pkgs/DevTools/pkg.info
simplebuild_dgcode/data/pkgs/DevTools/data/valgrind_suppressions.txt
simplebuild_dgcode/data/pkgs/DevTools/data/valgrind_suppressions_root.txt
simplebuild_dgcode/data/pkgs/DevTools/scripts/bin2asm
simplebuild_dgcode/data/pkgs/DevTools/scripts/callgrind
simplebuild_dgcode/data/pkgs/DevTools/scripts/depickle
simplebuild_dgcode/data/pkgs/DevTools/scripts/gdb
simplebuild_dgcode/data/pkgs/DevTools/scripts/gperfcpu
simplebuild_dgcode/data/pkgs/DevTools/scripts/installmpmath
simplebuild_dgcode/data/pkgs/DevTools/scripts/projdepana
simplebuild_dgcode/data/pkgs/DevTools/scripts/showcppdefines
simplebuild_dgcode/data/pkgs/DevTools/scripts/valfiles
simplebuild_dgcode/data/pkgs/DevTools/scripts/valgrind_helgrind
simplebuild_dgcode/data/pkgs/DevTools/scripts/valgrind_leakcheck
simplebuild_dgcode/data/pkgs/DevTools/scripts/valgrind_memcheck
simplebuild_dgcode/data/pkgs/DevTools/scripts/vtune
simplebuild_dgcode/data/pkgs/G4/Components/G4CollectFilters/pkg.info
simplebuild_dgcode/data/pkgs/G4/Components/G4CollectFilters/libinc/StepFilterPrimary.hh
simplebuild_dgcode/data/pkgs/G4/Components/G4CollectFilters/libinc/StepFilterTime.hh
simplebuild_dgcode/data/pkgs/G4/Components/G4CollectFilters/libinc/StepFilterVolume.hh
simplebuild_dgcode/data/pkgs/G4/Components/G4CollectFilters/libsrc/StepFilterPrimary.cc
simplebuild_dgcode/data/pkgs/G4/Components/G4CollectFilters/libsrc/StepFilterTime.cc
simplebuild_dgcode/data/pkgs/G4/Components/G4CollectFilters/libsrc/StepFilterVolume.cc
simplebuild_dgcode/data/pkgs/G4/Components/G4CollectFilters/pycpp_StepFilterPrimary/mod.cc
simple_build_dgcode-1.7.2.dist-info/METADATA
simple_build_dgcode-1.7.2.dist-info/WHEEL
simple_build_dgcode-1.7.2.dist-info/entry_points.txt
simple_build_dgcode-1.7.2.dist-info/top_level.txt
simple_build_dgcode-1.7.2.dist-info/RECORD
