Metadata-Version: 2.4
Name: simple-build-dgcode
Version: 1.7.2
Summary: The Geant4-based coding framework originating in the ESS Detector Group, provided as a simplebuild bundle of packages.
Author-email: Thomas Kittelmann <thomas.kittelmann@ess.eu>
License: The Apache 2.0 license is reproduced in the following. See the NOTICE file for
Project-URL: Homepage, https://mctools.github.io/simplebuild-dgcode/
Project-URL: Bug Tracker, https://github.com/mctools/simplebuild-dgcode/issues
Classifier: Programming Language :: Python :: 3
Classifier: License :: OSI Approved :: Apache Software License
Classifier: Operating System :: Unix
Requires-Python: >=3.8
License-File: LICENSE
Requires-Dist: simple-build-system>=1.7.1
Provides-Extra: recommended
Requires-Dist: numpy; extra == "recommended"
Requires-Dist: ncrystal>=4.2.10; extra == "recommended"
Requires-Dist: mcpl>=2.2.4; extra == "recommended"
Requires-Dist: matplotlib; extra == "recommended"
Provides-Extra: all
Requires-Dist: numpy; extra == "all"
Requires-Dist: ncrystal[all]>=4.2.10; extra == "all"
Requires-Dist: mcpl>=2.2.4; extra == "all"
Requires-Dist: matplotlib; extra == "all"
Requires-Dist: scipy; extra == "all"
Requires-Dist: pandas; extra == "all"
Requires-Dist: PySimpleGUI-4-foss; extra == "all"
Dynamic: license-file
